{"inkVersion":17,"root":[{"#":"left:Player"},{"#":"right:Colm"},{"#":"back:Desk"},{"->":"Intro"},"done",{"Intro":[["^<H3> Telegraph </H3>","\n","^(This is text)","\n",["ev",{"^->":"Intro.0.4.$r1"},{"temp=":"$r"},"str",{"->":".^.s"},[{"#n":"$r1"}],"/str","/ev",{"*":".^.c","flg":2},{"s":["^<i>Hello",{"->":"$r","var":true},null],"c":["ev",{"^->":"Intro.0.4.c.$r2"},"/ev",{"temp=":"$r"},{"->":".^.^.s"},[{"#n":"$r2"}],"\n","\n","^You said 'Hello!'","\n",{"->":".^.^.^.g-0"},{"#f":7}]}],["ev",{"^->":"Intro.0.5.$r1"},{"temp=":"$r"},"str",{"->":".^.s"},[{"#n":"$r1"}],"/str","/ev",{"*":".^.c","flg":2},{"s":["^<i>Hey",{"->":"$r","var":true},null],"c":["ev",{"^->":"Intro.0.5.c.$r2"},"/ev",{"temp=":"$r"},{"->":".^.^.s"},[{"#n":"$r2"}],"\n","\n","^You said hey!","\n",{"->":".^.^.^.g-0"},{"#f":7}]}],{"g-0":["^Now we are back together.","\n","end",{"#f":7}]}],{"#f":3}],"#f":3}],"listDefs":{}}